webedge/__init__.py
webedge/cli_output.py
webedge/social_websites.py
webedge/stop_words.py
webedge/warnings.py
webedge/webedge.py
webedge/webpage_analysis.py
webedge/website_analysis.py
WebEdge-1.0.2.dist-info/LICENSE
WebEdge-1.0.2.dist-info/METADATA
WebEdge-1.0.2.dist-info/WHEEL
WebEdge-1.0.2.dist-info/entry_points.txt
WebEdge-1.0.2.dist-info/top_level.txt
WebEdge-1.0.2.dist-info/RECORD
