Metadata-Version: 2.1
Name: WebEdge
Version: 1.0.2
Summary: Bringing Edge to your Web Performance
Home-page: https://github.com/HarshCasper/WebEdge
Author: MLH Fellowship Team 1
Author-email: erbeusgriffincasper@gmail.com
License: MIT License
Platform: UNKNOWN
License-File: LICENSE
Requires-Dist: appdirs (==1.4.3)
Requires-Dist: beautifulsoup4 (==4.9.3)
Requires-Dist: bs4 (==0.0.1)
Requires-Dist: CacheControl (==0.12.6)
Requires-Dist: certifi (==2019.11.28)
Requires-Dist: chardet (==3.0.4)
Requires-Dist: clanimate (==0.0.1)
Requires-Dist: click (==7.1.2)
Requires-Dist: colorama (==0.4.4)
Requires-Dist: contextlib2 (==0.6.0)
Requires-Dist: distlib (==0.3.0)
Requires-Dist: distro (==1.4.0)
Requires-Dist: html5lib (==1.0.1)
Requires-Dist: idna (==2.8)
Requires-Dist: ipaddr (==2.2.0)
Requires-Dist: joblib (==0.17.0)
Requires-Dist: lockfile (==0.12.2)
Requires-Dist: msgpack (==0.6.2)
Requires-Dist: nltk (==3.5)
Requires-Dist: packaging (==20.3)
Requires-Dist: pep517 (==0.8.2)
Requires-Dist: progress (==1.5)
Requires-Dist: prompt-toolkit (==1.0.14)
Requires-Dist: pyfiglet (==0.8.post1)
Requires-Dist: Pygments (==2.7.2)
Requires-Dist: PyInquirer (==1.0.3)
Requires-Dist: pyparsing (==2.4.6)
Requires-Dist: pytoml (==0.1.21)
Requires-Dist: pyyaml (==5.3.1)
Requires-Dist: regex (==2020.11.13)
Requires-Dist: requests (==2.25.0)
Requires-Dist: retrying (==1.3.3)
Requires-Dist: SentimentAnalysis (==0.8)
Requires-Dist: six (==1.15.0)
Requires-Dist: soupsieve (==2.0.1)
Requires-Dist: tqdm (==4.53.0)
Requires-Dist: urllib3 (==1.26.2)
Requires-Dist: vaderSentiment (==3.3.2)
Requires-Dist: wcwidth (==0.2.5)
Requires-Dist: webencodings (==0.5.1)
